[{"_fechaDeAlta":"03\/02\/2020 08:31:04.393","_id":1,"_marca":"Seat","_matricula":"TO2547AG","_modelo":"Panda"},{"_fechaDeAlta":"03\/02\/2020 08:31:04.407","_id":2,"_marca":"Alfa Romeo","_matricula":"2385BBC","_modelo":"Cordoba"},{"_fechaDeAlta":"04\/02\/2020 14:29:23.193","_id":6,"_marca":"Seat","_matricula":"Otro","_modelo":"Fura"},{"_fechaDeAlta":"04\/02\/2020 14:30:19.877","_id":7,"_marca":"Mercedes","_matricula":"M5555AB","_modelo":"200"},{"_fechaDeAlta":"04\/02\/2020 14:32:30.990","_id":8,"_marca":"Skoda","_matricula":"3636GHT","_modelo":"Fabia"},{"_fechaDeAlta":"04\/02\/2020 14:35:39.427","_id":9,"_marca":"Seat","_matricula":"5556ABC","_modelo":"Málaga"},{"_fechaDeAlta":"04\/02\/2020 15:13:53.807","_id":1004,"_marca":"Chrysler","_matricula":"TO6277AG","_modelo":"Stratus"},{"_fechaDeAlta":"04\/02\/2020 15:16:01.227","_id":1005,"_marca":"Alfa Romeo","_matricula":"BCD5555","_modelo":"75"},{"_fechaDeAlta":"04\/02\/2020 15:20:54.633","_id":1006,"_marca":"Volvo","_matricula":"BBF1122","_modelo":"740"},{"_fechaDeAlta":"04\/02\/2020 15:25:33.207","_id":1008,"_marca":"Audi","_matricula":"AV1524C","_modelo":"Trescientos"},{"_fechaDeAlta":"10\/02\/2020 09:00:11.817","_id":2005,"_marca":"aaaa","_matricula":"2514GFT","_modelo":"gggg"},{"_fechaDeAlta":"10\/02\/2020 09:02:13.380","_id":2007,"_marca":"gggg","_matricula":"gggg","_modelo":"gggg"},{"_fechaDeAlta":"10\/02\/2020 09:02:28.467","_id":2008,"_marca":"hhh","_matricula":"hhh","_modelo":"hhhh"},{"_fechaDeAlta":"10\/02\/2020 09:03:35.283","_id":2009,"_marca":"fdgfdsg","_matricula":"gggg","_modelo":"75"},{"_fechaDeAlta":"10\/02\/2020 09:05:35.623","_id":2010,"_marca":"dfsf","_matricula":"ffff","_modelo":"sfad"},{"_fechaDeAlta":"10\/02\/2020 09:06:36.407","_id":2011,"_marca":"yyyy","_matricula":"yyyy","_modelo":"yyy"},{"_fechaDeAlta":"10\/02\/2020 09:14:32.220","_id":2012,"_marca":"sdafd","_matricula":"dsfasdf","_modelo":"sdafsd"},{"_fechaDeAlta":"10\/02\/2020 09:15:34.990","_id":2013,"_marca":"sdfasdf","_matricula":"sdfasdf","_modelo":"dssdfaf"},{"_fechaDeAlta":"10\/02\/2020 09:15:55.823","_id":2014,"_marca":"sdfasdf","_matricula":"afsd","_modelo":"sdafdf"},{"_fechaDeAlta":"10\/02\/2020 09:16:21.133","_id":2015,"_marca":"asfsdf","_matricula":"666","_modelo":"sdafd"},{"_fechaDeAlta":"10\/02\/2020 09:16:59.690","_id":2016,"_marca":"adfaf","_matricula":"Otro1","_modelo":"adsfa"},{"_fechaDeAlta":"10\/02\/2020 09:23:56.350","_id":2017,"_marca":"sdfaf","_matricula":"dsfasf","_modelo":"sadf"},{"_fechaDeAlta":"10\/02\/2020 09:24:13.000","_id":2018,"_marca":"sdfadfa","_matricula":"adsfsad","_modelo":"asdfdasf"},{"_fechaDeAlta":"10\/02\/2020 09:24:20.880","_id":2019,"_marca":"sdfsadf","_matricula":"adsfssdf","_modelo":"sdfsadf"},{"_fechaDeAlta":"10\/02\/2020 09:24:31.517","_id":2020,"_marca":"sadfdf","_matricula":"dsafsds","_modelo":"sadff"}]